{"version":"3.9.2","examples":[{"id":"./spec/invoices/employer_invoice_spec.rb[1:1:1:1]","description":"should trigger notice","full_description":"EmployerInvoice.send_first_invoice_available_notice For initial Employers should trigger notice","status":"passed","file_path":"./spec/invoices/employer_invoice_spec.rb","line_number":18,"run_time":0.72737706,"pending_message":null},{"id":"./spec/invoices/employer_invoice_spec.rb[1:1:2:1]","description":"should trigger notice for employer with initial plan year only","full_description":"EmployerInvoice.send_first_invoice_available_notice For Conversion Employers should trigger notice for employer with initial plan year only","status":"passed","file_path":"./spec/invoices/employer_invoice_spec.rb","line_number":27,"run_time":0.712116766,"pending_message":null},{"id":"./spec/invoices/employer_invoice_spec.rb[1:1:2:2]","description":"should not trigger notice for employer with renewal plan year","full_description":"EmployerInvoice.send_first_invoice_available_notice For Conversion Employers should not trigger notice for employer with renewal plan year","status":"passed","file_path":"./spec/invoices/employer_invoice_spec.rb","line_number":32,"run_time":0.714599298,"pending_message":null},{"id":"./spec/invoices/invoice_helper_spec.rb[1:1:1]","description":"returns mailing address if only mailing address is present","full_description":"InvoiceHelper#mailing_or_primary_address returns mailing address if only mailing address is present","status":"passed","file_path":"./spec/invoices/invoice_helper_spec.rb","line_number":15,"run_time":0.003004838,"pending_message":null},{"id":"./spec/invoices/invoice_helper_spec.rb[1:1:2]","description":"returns mailing address if both mailing and primary addresses are present","full_description":"InvoiceHelper#mailing_or_primary_address returns mailing address if both mailing and primary addresses are present","status":"passed","file_path":"./spec/invoices/invoice_helper_spec.rb","line_number":21,"run_time":0.001111814,"pending_message":null},{"id":"./spec/invoices/invoice_helper_spec.rb[1:1:3]","description":"returns primary address if mailing address is not present","full_description":"InvoiceHelper#mailing_or_primary_address returns primary address if mailing address is not present","status":"passed","file_path":"./spec/invoices/invoice_helper_spec.rb","line_number":28,"run_time":0.00075861,"pending_message":null}],"summary":{"duration":2.161981324,"example_count":6,"failure_count":0,"pending_count":0,"errors_outside_of_examples_count":0},"summary_line":"6 examples, 0 failures"}